Workbook

Sheet Cover
B5: WIPRO LIMITED
B7: Discounted Cash Flow (DCF) Valuation Model
B13: WORKSHEET INDEX
B35: All figures in INR Crores unless stated otherwise | Sources: Wipro Annual Reports, NSE/BSE
B41: 1 | C41: Historical Financials | E41: 5-year audited data (FY20–FY24)
B43: 2 | C43: Assumptions | E43: WACC, growth, margin assumptions
B45: 3 | C45: Financial Forecasts | E45: Projected P&L & FCF (FY25E–FY29E)
B47: 4 | C47: DCF Valuation | E47: Enterprise Value & Intrinsic Share Price

Sheet Historical Financials
B1: WIPRO LIMITED — Historical Financial Summary (FY2020–FY2024)
B2: All figures in INR Crores | Source: Wipro Annual Reports
B4: Line Item | C4: FY2020 | D4: FY2021 | E4: FY2022 | F4: FY2023 | G4: FY2024
B5: INCOME STATEMENT
B6: Revenue from Operations | C6: 61943 | D6: 62965 | E6: 79312 | F6: 90488 | G6: 97285
B7: YoY Growth (%) | C7: — | D7: =(D6-C6)/C6 -> 0.016499039 | E7: =(E6-D6)/D6 -> 0.25962042 | F7: =(F6-E6)/E6 -> 0.14091184 | G7: =(G6-F6)/F6 -> 0.075114932
B8: Cost of Revenues | C8: 42351 | D8: 43038 | E8: 54437 | F8: 62571 | G8: 67450
B9: Gross Profit | C9: =C6-C8 -> 19592 | D9: =D6-D8 -> 19927 | E9: =E6-E8 -> 24875 | F9: =F6-F8 -> 27917 | G9: =G6-G8 -> 29835
B10: Gross Margin (%) | C10: =C9/C6 -> 0.31629078 | D10: =D9/D6 -> 0.31647741 | E10: =E9/E6 -> 0.31363476 | F10: =F9/F6 -> 0.30851605 | G10: =G9/G6 -> 0.30667626
B11: SG&A Expenses | C11: 8932 | D11: 8756 | E11: 10211 | F11: 11489 | G11: 12108
B12: EBITDA | C12: =C9-C11 -> 10660 | D12: =D9-D11 -> 11171 | E12: =E9-E11 -> 14664 | F12: =F9-F11 -> 16428 | G12: =G9-G11 -> 17727
B13: EBITDA Margin (%) | C13: =C12/C6 -> 0.1720937 | D13: =D12/D6 -> 0.17741602 | E13: =E12/E6 -> 0.18489005 | F13: =F12/F6 -> 0.18154893 | G13: =G12/G6 -> 0.1822172
B14: Depreciation & Amort. | C14: 2891 | D14: 3124 | E14: 3456 | F14: 3789 | G14: 4021
B15: EBIT | C15: =C12-C14 -> 7769 | D15: =D12-D14 -> 8047 | E15: =E12-E14 -> 11208 | F15: =F12-F14 -> 12639 | G15: =G12-G14 -> 13706
B16: EBIT Margin (%) | C16: =C15/C6 -> 0.12542176 | D16: =D15/D6 -> 0.12780116 | E16: =E15/E6 -> 0.14131531 | F16: =F15/F6 -> 0.13967598 | G16: =G15/G6 -> 0.14088503
B17: Interest Expense | C17: 312 | D17: 298 | E17: 425 | F17: 534 | G17: 498
B18: PBT | C18: =C15-C17 -> 7457 | D18: =D15-D17 -> 7749 | E18: =E15-E17 -> 10783 | F18: =F15-F17 -> 12105 | G18: =G15-G17 -> 13208
B19: Tax | C19: 2245 | D19: 2398 | E19: 3012 | F19: 3456 | G19: 3892
B20: Net Income (PAT) | C20: =C18-C19 -> 5212 | D20: =D18-D19 -> 5351 | E20: =E18-E19 -> 7771 | F20: =F18-F19 -> 8649 | G20: =G18-G19 -> 9316
B21: Net Margin (%) | C21: =C20/C6 -> 0.084141872 | D21: =D20/D6 -> 0.084983721 | E21: =E20/E6 -> 0.097980129 | F21: =F20/F6 -> 0.095581735 | G21: =G20/G6 -> 0.095759881
B23: CASH FLOW & BALANCE SHEET ITEMS
B24: Operating Cash Flow (OCF) | C24: 9456 | D24: 10234 | E24: 13456 | F24: 14892 | G24: 16234
B25: Capital Expenditure (CapEx) | C25: 2134 | D25: 1987 | E25: 2456 | F25: 2789 | G25: 3012
B26: Free Cash Flow (FCF) | C26: =C24-C25 -> 7322 | D26: =D24-D25 -> 8247 | E26: =E24-E25 -> 11000 | F26: =F24-F25 -> 12103 | G26: =G24-G25 -> 13222
B27: FCF Margin (%) | C27: =C26/C6 -> 0.11820545 | D27: =D26/D6 -> 0.13097753 | E27: =E26/E6 -> 0.13869276 | F27: =F26/F6 -> 0.13375254 | G27: =G26/G6 -> 0.13590996
B28: Total Debt | C28: 3456 | D28: 3012 | E28: 4234 | F28: 4891 | G28: 4234
B29: Cash & Equivalents | C29: 12456 | D29: 15234 | E29: 18912 | F29: 22345 | G29: 28456
B30: Net Debt / (Net Cash) | C30: =C28-C29 -> -9000 | D30: =D28-D29 -> -12222 | E30: =E28-E29 -> -14678 | F30: =F28-F29 -> -17454 | G30: =G28-G29 -> -24222
B31: Total Equity (Book) | C31: 42345 | D31: 47891 | E31: 54234 | F31: 61789 | G31: 68456
B33: KEY FINANCIAL RATIOS
B34: Return on Equity (ROE) | C34: =C20/C31 -> 0.12308419 | D34: =D20/D31 -> 0.11173289 | E34: =E20/E31 -> 0.1432865 | F34: =F20/F31 -> 0.13997637 | G34: =G20/G31 -> 0.13608741
B35: Return on Capital (ROCE) | C35: =C15/(C28+C31) -> 0.16962512 | D35: =D15/(D28+D31) -> 0.15808499 | E35: =E15/(E28+E31) -> 0.1916946 | F35: =F15/(F28+F31) -> 0.18954709 | G35: =G15/(G28+G31) -> 0.18855413
B36: D/E Ratio | C36: =C28/C31 -> 0.081615303 | D36: =D28/D31 -> 0.062892819 | E36: =E28/E31 -> 0.078069108 | F36: =F28/F31 -> 0.079156484 | G36: =G28/G31 -> 0.061849947
B37: Revenue / Employee (₹ Cr) | C37: =C6/212535 -> 0.29144847 | D37: =D6/197452 -> 0.31888763 | E37: =E6/240899 -> 0.32923341 | F37: =F6/258865 -> 0.34955672 | G37: =G6/234054 -> 0.41565194
B39: Note: Revenue data sourced from Wipro Annual Report / NSE filings. Figures are approximate for illustration; verify against official filings before use.

Sheet Assumptions
B1: WIPRO LIMITED — Model Assumptions & WACC
B3: Assumption | C3: Value / Input | D3: Notes & Rationale
B4: Revenue Growth — FY2025E | C4: 0.09 | D4: 9% — consensus analyst estimate; reflects IT sector recovery
B5: Revenue Growth — FY2026E | C5: 0.1 | D5: 10% — demand acceleration in cloud & AI services
B6: Revenue Growth — FY2027E | C6: 0.11 | D6: 11% — organic growth + Capco synergies
B7: Revenue Growth — FY2028E | C7: 0.1 | D7: 10% — growth moderation towards industry steady state
B8: Revenue Growth — FY2029E | C8: 0.09 | D8: 9% — normalised long-run growth
B10: Assumption | C10: Value / Input | D10: Notes & Rationale
B11: EBIT Margin (FY25E–FY27E) | C11: 0.155 | D11: 15.5% — Wipro FY24 EBIT margin ~14.9%; slight expansion
B12: EBIT Margin (FY28E–FY29E) | C12: 0.16 | D12: 16.0% — gradual improvement; sector avg ~17%
B13: D&A as % of Revenue | C13: 0.042 | D13: 4.2% — consistent with historical 4.0–4.4% range
B14: CapEx as % of Revenue | C14: 0.031 | D14: 3.1% — asset-light IT model; historical ~3.0–3.3%
B15: Change in NWC as % Rev | C15: -0.005 | D15: −0.5% of revenue; negative = cash inflow
B17: Assumption | C17: Value / Input | D17: Notes & Rationale
B18: Effective Tax Rate | C18: 0.255 | D18: 25.5% — India corp. tax rate for large companies (Section 115BAA excluded)
B20: Assumption | C20: Value / Input | D20: Notes & Rationale
B21: Risk-Free Rate (Rf) | C21: 0.072 | D21: 7.2% — India 10-year G-Sec yield (Mar 2024)
B22: Equity Risk Premium (ERP) | C22: 0.06 | D22: 6.0% — Damodaran India ERP estimate
B23: Beta (β) | C23: 0.85 | D23: 0.85 — Wipro 5-yr monthly beta vs NIFTY 50 (Bloomberg)
B24: Cost of Equity (Ke) | C24: =C21+C23*C22 -> 0.123 | D24: CAPM: Rf + β × ERP
B25: Pre-Tax Cost of Debt (Kd) | C25: 0.085 | D25: 8.5% — Wipro's marginal borrowing rate (NCD yield)
B26: Tax Rate | C26: =C18 -> 0.255 | D26: Links to Tax Rate assumption above
B27: After-Tax Cost of Debt | C27: =C25*(1-C26) -> 0.063325 | D27: Kd × (1 − Tax Rate)
B28: Weight of Equity (We) | C28: 0.92 | D28: 92% — Wipro capital structure (near debt-free)
B29: Weight of Debt (Wd) | C29: =1-C28 -> 0.08 | D29: 1 − We
B30: WACC | C30: =C28*C24+C29*C27 -> 0.118226 | D30: We×Ke + Wd×Kd(1-T) ← KEY DISCOUNT RATE
B32: Assumption | C32: Value / Input | D32: Notes & Rationale
B33: Terminal Growth Rate (g) | C33: 0.045 | D33: 4.5% — long-run nominal GDP growth rate for India IT sector
B34: Terminal Year FCFF | C34: → linked from Forecasts sheet | D34: Auto-linked in DCF sheet
B36: Yellow cells = user inputs. Change these to run scenario analysis. Blue cells = formula-derived.

Sheet Financial Forecasts
B1: WIPRO LIMITED — Financial Forecasts & Free Cash Flow (FY2025E–FY2029E)
B2: All figures in INR Crores | Assumptions sourced from 'Assumptions' sheet
B4: Line Item | C4: FY2025E | D4: FY2026E | E4: FY2027E | F4: FY2028E | G4: FY2029E
B5: PROJECTED INCOME STATEMENT
B6: Revenue from Operations | C6: ='Historical Financials'!G6*(1+Assumptions!C4) -> 106040.65 | D6: =C6*(1+Assumptions!C5) -> 116644.72 | E6: =D6*(1+Assumptions!C6) -> 129475.63 | F6: =E6*(1+Assumptions!C7) -> 142423.2 | G6: =F6*(1+Assumptions!C8) -> 155241.28
B7: YoY Growth (%) | C7: =C6/'Historical Financials'!G6-1 -> 0.09 | D7: =D6/C6-1 -> 0.1 | E7: =E6/D6-1 -> 0.11 | F7: =F6/E6-1 -> 0.1 | G7: =G6/F6-1 -> 0.09
B8: EBIT | C8: =C6*Assumptions!$C$11 -> 16436.301 | D8: =D6*Assumptions!$C$11 -> 18079.931 | E8: =E6*Assumptions!$C$11 -> 20068.723 | F8: =F6*Assumptions!$C$12 -> 22787.712 | G8: =G6*Assumptions!$C$12 -> 24838.606
B9: EBIT Margin (%) | C9: =C8/C6 -> 0.155 | D9: =D8/D6 -> 0.155 | E9: =E8/E6 -> 0.155 | F9: =F8/F6 -> 0.16 | G9: =G8/G6 -> 0.16
B10: Depreciation & Amort. | C10: =C6*Assumptions!$C$13 -> 4453.7073 | D10: =D6*Assumptions!$C$13 -> 4899.078 | E10: =E6*Assumptions!$C$13 -> 5437.9766 | F10: =F6*Assumptions!$C$13 -> 5981.7743 | G10: =G6*Assumptions!$C$13 -> 6520.134
B11: EBIT (for NOPAT) | C11: =C8 -> 16436.301 | D11: =D8 -> 18079.931 | E11: =E8 -> 20068.723 | F11: =F8 -> 22787.712 | G11: =G8 -> 24838.606
B12: NOPAT (EBIT×(1−Tax)) | C12: =C11*(1-Assumptions!$C$18) -> 12245.044 | D12: =D11*(1-Assumptions!$C$18) -> 13469.548 | E12: =E11*(1-Assumptions!$C$18) -> 14951.199 | F12: =F11*(1-Assumptions!$C$18) -> 16976.845 | G12: =G11*(1-Assumptions!$C$18) -> 18504.761
B13: Add: Depreciation | C13: =C10 -> 4453.7073 | D13: =D10 -> 4899.078 | E13: =E10 -> 5437.9766 | F13: =F10 -> 5981.7743 | G13: =G10 -> 6520.134
B14: Less: Capital Expenditure | C14: =-C6*Assumptions!$C$14 -> -3287.2602 | D14: =-D6*Assumptions!$C$14 -> -3615.9862 | E14: =-E6*Assumptions!$C$14 -> -4013.7446 | F14: =-F6*Assumptions!$C$14 -> -4415.1191 | G14: =-G6*Assumptions!$C$14 -> -4812.4798
B15: Less: Change in NWC | C15: =C6*Assumptions!$C$15 -> -530.20325 | D15: =D6*Assumptions!$C$15 -> -583.22358 | E15: =E6*Assumptions!$C$15 -> -647.37817 | F15: =F6*Assumptions!$C$15 -> -712.11599 | G15: =G6*Assumptions!$C$15 -> -776.20642
B16: Free Cash Flow to Firm (FCFF) | C16: =C12+C13+C14+C15 -> 12881.288 | D16: =D12+D13+D14+D15 -> 14169.417 | E16: =E12+E13+E14+E15 -> 15728.053 | F16: =F12+F13+F14+F15 -> 17831.384 | G16: =G12+G13+G14+G15 -> 19436.209
B17: FCF Margin (%) | C17: =C16/C6 -> 0.121475 | D17: =D16/D6 -> 0.121475 | E17: =E16/E6 -> 0.121475 | F17: =F16/F6 -> 0.1252 | G17: =G16/G6 -> 0.1252
B20: Note: FCFF = NOPAT + D&A − CapEx − ΔNWC. Negative NWC change implies working capital improvement (cash inflow).

Sheet DCF Valuation
B1: WIPRO LIMITED — DCF Valuation Summary
B3: STEP 1 — DISCOUNTED FREE CASH FLOWS
B4: Line Item | C4: FY2025E | D4: FY2026E | E4: FY2027E | F4: FY2028E | G4: FY2029E
B5: Free Cash Flow to Firm (FCFF) | C5: ='Financial Forecasts'!C16 -> 12881.288 | D5: ='Financial Forecasts'!D16 -> 14169.417 | E5: ='Financial Forecasts'!E16 -> 15728.053 | F5: ='Financial Forecasts'!F16 -> 17831.384 | G5: ='Financial Forecasts'!G16 -> 19436.209
B6: Discount Period (t) | C6: 1 | D6: 2 | E6: 3 | F6: 4 | G6: 5
B7: Discount Factor [1/(1+WACC)^t] | C7: =1/(1+Assumptions!$C$31)^C6 -> 1 | D7: =1/(1+Assumptions!$C$31)^D6 -> 1 | E7: =1/(1+Assumptions!$C$31)^E6 -> 1 | F7: =1/(1+Assumptions!$C$31)^F6 -> 1 | G7: =1/(1+Assumptions!$C$31)^G6 -> 1
B8: PV of FCFF | C8: =C5*C7 -> 12881.288 | D8: =D5*D7 -> 14169.417 | E8: =E5*E7 -> 15728.053 | F8: =F5*F7 -> 17831.384 | G8: =G5*G7 -> 19436.209
B10: STEP 2 — TERMINAL VALUE (Gordon Growth Model)
B11: Terminal Year FCFF (FY2029E) | C11: ='Financial Forecasts'!G16 -> 19436.209
B12: Terminal Growth Rate (g) | C12: =Assumptions!C33 -> 0.045
B13: WACC | C13: =Assumptions!C31 -> 0
B14: Terminal Value [FCFF×(1+g)/(WACC−g)] | C14: =C11*(1+C12)/(C13-C12) -> -451351.96
B15: PV of Terminal Value [TV/(1+WACC)^5] | C15: =C14/(1+Assumptions!$C$31)^5 -> -451351.96
B17: STEP 3 — ENTERPRISE VALUE & EQUITY VALUE
B18: Sum of PV of FCFFs | C18: =SUM(C8:G8) -> 80046.35
B19: PV of Terminal Value | C19: =C15 -> -451351.96
B20: Enterprise Value (EV) | C20: =C18+C19 -> -371305.61
B21: Less: Total Debt | C21: =-'Historical Financials'!G28 -> -4234
B22: Add: Cash & Equivalents | C22: ='Historical Financials'!G29 -> 28456
B23: Equity Value | C23: =C20+C21+C22 -> -347083.61
B24: Shares Outstanding (Crores) | C24: 523
B25: Intrinsic Value per Share (INR) | C25: =C23/C24 -> -663.63979
B26: Current Market Price (INR) | C26: 480
B27: Upside / (Downside) Potential (%) | C27: =(C25-C26)/C26 -> -2.3825829
B28: Valuation Verdict | C28: =IF(C25>C26,"UNDERVALUED ✓","OVERVALUED ✗") -> OVERVALUED ✗
B30: STEP 4 — SENSITIVITY ANALYSIS (Intrinsic Share Price in INR)
B31: WACC → (g ↓) | C31: 0.09 | D31: 0.1 | E31: 0.11 | F31: 0.12 | G31: 0.13
B32: 0.03 | C32: =(('Financial Forecasts'!G16*(1+0.03)/(0.09-0.03))/(1+0.09)^5+SUM('DCF Valuation'!C8:G8)+'Historical Financials'!G29-'Historical Financials'!G28)/'DCF Valuation'!C24 -> 613.99838 | D32: =(('Financial Forecasts'!G16*(1+0.03)/(0.1-0.03))/(1+0.1)^5+SUM('DCF Valuation'!C8:G8)+'Historical Financials'!G29-'Historical Financials'!G28)/'DCF Valuation'!C24 -> 538.90171 | E32: =(('Financial Forecasts'!G16*(1+0.03)/(0.11-0.03))/(1+0.11)^5+SUM('DCF Valuation'!C8:G8)+'Historical Financials'!G29-'Historical Financials'!G28)/'DCF Valuation'!C24 -> 483.31609 | F32: =(('Financial Forecasts'!G16*(1+0.03)/(0.12-0.03))/(1+0.12)^5+SUM('DCF Valuation'!C8:G8)+'Historical Financials'!G29-'Historical Financials'!G28)/'DCF Valuation'!C24 -> 440.69763 | G32: =(('Financial Forecasts'!G16*(1+0.03)/(0.13-0.03))/(1+0.13)^5+SUM('DCF Valuation'!C8:G8)+'Historical Financials'!G29-'Historical Financials'!G28)/'DCF Valuation'!C24 -> 407.12249
B33: 0.035 | C33: =(('Financial Forecasts'!G16*(1+0.035)/(0.09-0.035))/(1+0.09)^5+SUM('DCF Valuation'!C8:G8)+'Historical Financials'!G29-'Historical Financials'!G28)/'DCF Valuation'!C24 -> 653.88801 | D33: =(('Financial Forecasts'!G16*(1+0.035)/(0.1-0.035))/(1+0.1)^5+SUM('DCF Valuation'!C8:G8)+'Historical Financials'!G29-'Historical Financials'!G28)/'DCF Valuation'!C24 -> 566.79487 | E33: =(('Financial Forecasts'!G16*(1+0.035)/(0.11-0.035))/(1+0.11)^5+SUM('DCF Valuation'!C8:G8)+'Historical Financials'!G29-'Historical Financials'!G28)/'DCF Valuation'!C24 -> 503.7164 | F33: =(('Financial Forecasts'!G16*(1+0.035)/(0.12-0.035))/(1+0.12)^5+SUM('DCF Valuation'!C8:G8)+'Historical Financials'!G29-'Historical Financials'!G28)/'DCF Valuation'!C24 -> 456.13404 | G33: =(('Financial Forecasts'!G16*(1+0.035)/(0.13-0.035))/(1+0.13)^5+SUM('DCF Valuation'!C8:G8)+'Historical Financials'!G29-'Historical Financials'!G28)/'DCF Valuation'!C24 -> 419.11866
B34: 0.04 | C34: =(('Financial Forecasts'!G16*(1+0.04)/(0.09-0.04))/(1+0.09)^5+SUM('DCF Valuation'!C8:G8)+'Historical Financials'!G29-'Historical Financials'!G28)/'DCF Valuation'!C24 -> 701.75556 | D34: =(('Financial Forecasts'!G16*(1+0.04)/(0.1-0.04))/(1+0.1)^5+SUM('DCF Valuation'!C8:G8)+'Historical Financials'!G29-'Historical Financials'!G28)/'DCF Valuation'!C24 -> 599.3369 | E34: =(('Financial Forecasts'!G16*(1+0.04)/(0.11-0.04))/(1+0.11)^5+SUM('DCF Valuation'!C8:G8)+'Historical Financials'!G29-'Historical Financials'!G28)/'DCF Valuation'!C24 -> 527.03104 | F34: =(('Financial Forecasts'!G16*(1+0.04)/(0.12-0.04))/(1+0.12)^5+SUM('DCF Valuation'!C8:G8)+'Historical Financials'!G29-'Historical Financials'!G28)/'DCF Valuation'!C24 -> 473.5 | G34: =(('Financial Forecasts'!G16*(1+0.04)/(0.13-0.04))/(1+0.13)^5+SUM('DCF Valuation'!C8:G8)+'Historical Financials'!G29-'Historical Financials'!G28)/'DCF Valuation'!C24 -> 432.44773
B35: 0.045 | C35: =(('Financial Forecasts'!G16*(1+0.045)/(0.09-0.045))/(1+0.09)^5+SUM('DCF Valuation'!C8:G8)+'Historical Financials'!G29-'Historical Financials'!G28)/'DCF Valuation'!C24 -> 760.26034 | D35: =(('Financial Forecasts'!G16*(1+0.045)/(0.1-0.045))/(1+0.1)^5+SUM('DCF Valuation'!C8:G8)+'Historical Financials'!G29-'Historical Financials'!G28)/'DCF Valuation'!C24 -> 637.79565 | E35: =(('Financial Forecasts'!G16*(1+0.045)/(0.11-0.045))/(1+0.11)^5+SUM('DCF Valuation'!C8:G8)+'Historical Financials'!G29-'Historical Financials'!G28)/'DCF Valuation'!C24 -> 553.93254 | F35: =(('Financial Forecasts'!G16*(1+0.045)/(0.12-0.045))/(1+0.12)^5+SUM('DCF Valuation'!C8:G8)+'Historical Financials'!G29-'Historical Financials'!G28)/'DCF Valuation'!C24 -> 493.18142 | G35: =(('Financial Forecasts'!G16*(1+0.045)/(0.13-0.045))/(1+0.13)^5+SUM('DCF Valuation'!C8:G8)+'Historical Financials'!G29-'Historical Financials'!G28)/'DCF Valuation'!C24 -> 447.34493
B36: 0.05 | C36: =(('Financial Forecasts'!G16*(1+0.05)/(0.09-0.05))/(1+0.09)^5+SUM('DCF Valuation'!C8:G8)+'Historical Financials'!G29-'Historical Financials'!G28)/'DCF Valuation'!C24 -> 833.39131 | D36: =(('Financial Forecasts'!G16*(1+0.05)/(0.1-0.05))/(1+0.1)^5+SUM('DCF Valuation'!C8:G8)+'Historical Financials'!G29-'Historical Financials'!G28)/'DCF Valuation'!C24 -> 683.94615 | E36: =(('Financial Forecasts'!G16*(1+0.05)/(0.11-0.05))/(1+0.11)^5+SUM('DCF Valuation'!C8:G8)+'Historical Financials'!G29-'Historical Financials'!G28)/'DCF Valuation'!C24 -> 585.31763 | F36: =(('Financial Forecasts'!G16*(1+0.05)/(0.12-0.05))/(1+0.12)^5+SUM('DCF Valuation'!C8:G8)+'Historical Financials'!G29-'Historical Financials'!G28)/'DCF Valuation'!C24 -> 515.67448 | G36: =(('Financial Forecasts'!G16*(1+0.05)/(0.13-0.05))/(1+0.13)^5+SUM('DCF Valuation'!C8:G8)+'Historical Financials'!G29-'Historical Financials'!G28)/'DCF Valuation'!C24 -> 464.10428
B38: Yellow = base case | Intrinsic prices above ₹480 (current market price) indicate upside. Sensitivity shows how share price changes with WACC and terminal growth rate assumptions.
B40: STEP 5 — INTERPRETATION & INVESTMENT CONCLUSION
B41: • Enterprise Value represents the total value of the business (debt + equity).
B42: • Intrinsic value per share is derived by subtracting net debt and dividing by shares.
B43: • If Intrinsic Value > Market Price → Stock is UNDERVALUED → Potential BUY signal
B44: • If Intrinsic Value < Market Price → Stock is OVERVALUED → Potential SELL/HOLD signal
B45: • Key model risk: DCF is highly sensitive to WACC and Terminal Growth Rate.
B46: • Always cross-check with comparable multiples (EV/EBITDA, P/E) and management guidance.
